CHANGES.txt
LICENSE.txt
MANIFEST.in
README.md
requirements.txt
setup.cfg
setup.py
pyspatial/__init__.py
pyspatial/dataset.py
pyspatial/fileutils.py
pyspatial/geoio.py
pyspatial/globalmaptiles.py
pyspatial/py3.py
pyspatial/raster.py
pyspatial/spatiallib.c
pyspatial/spatiallib.pyx
pyspatial/utils.py
pyspatial/vector.py
pyspatial/visualize.py
pyspatial.egg-info/PKG-INFO
pyspatial.egg-info/SOURCES.txt
pyspatial.egg-info/dependency_links.txt
pyspatial.egg-info/requires.txt
pyspatial.egg-info/top_level.txt
pyspatial/templates/app.js
pyspatial/templates/map.html
pyspatial/templates/css/base.css
pyspatial/templates/css/table.css
scripts/make_catalog_file
scripts/make_index
test/test_area.py
test/test_fileutils.py
test/test_raster.py
test/test_raster_band.py
test/test_raster_query.py
test/test_small_polygons.py
test/test_tiled.py
test/test_tiledwebraster.py
test/test_vector.py
test/test_visualize.py