Metadata-Version: 1.1
Name: pyspatial
Version: 0.2.4
Summary: Data structures for working with (geo)spatial data
Home-page: https://github.com/granularag/pyspatial
Author: Aman Thakral
Author-email: UNKNOWN
License: BSD
Keywords: spatial raster vector shapefile geojson data visualization pandas shapely gis geojson geographic geo
Platform: UNKNOWN
Classifier: Development Status :: 4 - Beta
Classifier: Topic :: Scientific/Engineering :: GIS
Classifier: License :: OSI Approved :: BSD License
